bcsim/__init__.py
bcsim/__main__.py
bcsim/clocks.py
bcsim/rail.py
bcsim/tools.py
bcsim-1.0.6.dist-info/entry_points.txt
bcsim-1.0.6.dist-info/LICENSE
bcsim-1.0.6.dist-info/WHEEL
bcsim-1.0.6.dist-info/METADATA
bcsim-1.0.6.dist-info/RECORD
