Metadata-Version: 2.1
Name: bcsim
Version: 1.0.6
Summary: Rolling Ball Clock Simulator
License: MIT
Keywords: bcsim,rolling,ball,clock,simulator
Author: Peter Nardi
Author-email: pete@nardi.com
Maintainer: Peter Nardi
Maintainer-email: pete@nardi.com
Requires-Python: >=3.7,<4.0
Classifier: Development Status :: 5 - Production/Stable
Classifier: Intended Audience :: Education
Classifier: Intended Audience :: End Users/Desktop
Classifier: License :: OSI Approved :: MIT License
Classifier: Natural Language :: English
Classifier: Operating System :: OS Independent
Classifier: Programming Language :: Python :: 3
Classifier: Programming Language :: Python :: 3.7
Classifier: Programming Language :: Python :: 3.8
Classifier: Programming Language :: Python :: 3.9
Classifier: Programming Language :: Python :: 3.10
Classifier: Programming Language :: Python :: 3.11
Classifier: Programming Language :: Python :: 3.10
Classifier: Programming Language :: Python :: 3.11
Classifier: Programming Language :: Python :: 3.7
Classifier: Programming Language :: Python :: 3.8
Classifier: Programming Language :: Python :: 3.9
Classifier: Topic :: Education
Classifier: Topic :: Games/Entertainment :: Simulation
Project-URL: Bug Tracker, https://github.com/geozeke/bcsim/issues
Project-URL: Documentation, https://geozeke.github.io/bcsim
Project-URL: Source Code, https://github.com/geozeke/bcsim
